setup.py
moven/__init__.py
moven/moven.py
moven.egg-info/PKG-INFO
moven.egg-info/SOURCES.txt
moven.egg-info/dependency_links.txt
moven.egg-info/entry_points.txt
moven.egg-info/requires.txt
moven.egg-info/top_level.txt