Metadata-Version: 1.1
Name: moven
Version: 0.2.0
Summary: NLP models distribution relying on Maven infrastructure
Home-page: https://bitbucket.org/ssix-project/moven
Author: Sergio Fernández
Author-email: sergio.fernandez@redlink.co
License: UNKNOWN
Keywords: python nlp ml dl models maven ssix
Platform: any
Classifier: Development Status :: 4 - Beta
Classifier: Intended Audience :: Developers
Classifier: Topic :: Software Development :: Build Tools
Classifier: Programming Language :: Python :: 2
Classifier: Programming Language :: Python :: 3
Classifier: Programming Language :: Java
Classifier: Environment :: Console
